[
  {
    "name": "Marcos Urena",
    "introduction": "Desarrollador Frontend Mid-Level con 4 anos de experiencia. Apasionado por la creacion de paneles administrativos complejos y el manejo eficiente del estado en el cliente utilizando arquitecturas modernas.",
    "contactInformation": {
      "email": "murena.front@example.com",
      "phone": "+506 8888 1234",
      "website": "github.com/marcosu-front"
    },
    "workExperience": [
      {
        "company": "TechNova Solutions",
        "startDate": "2022-01",
        "endDate": "Present",
        "position": "Frontend Developer",
        "description": "Desarrollo de un dashboard profesional utilizando las ultimas versiones de Angular. Implementacion de modulos de carga perezosa (lazy-loading), standalone components y reactividad avanzada con signals."
      },
      {
        "company": "Digital Agency CR",
        "startDate": "2020-05",
        "endDate": "2021-12",
        "position": "Junior Web Developer",
        "description": "Maquetacion de sitios web y consumo de APIs RESTful para clientes del sector retail."
      }
    ],
    "education": [
      {
        "institution": "Universidad Nacional",
        "degree": "Bachillerato",
        "title": "Ingenieria en Sistemas de Informacion",
        "startDate": "2016",
        "endDate": "2020"
      }
    ],
    "skills": [
      "angular",
      "typescript",
      "javascript",
      "html_css",
      "reactive_programming",
      "git",
      "rest_api"
    ]
  },
  {
    "name": "Valeria Sanchez",
    "introduction": "Ingeniera Fullstack Mid-Level. Experiencia solida en la construccion de sistemas de gestion de usuarios y despliegues automatizados, con un enfoque en la calidad del codigo y pruebas integrales.",
    "contactInformation": {
      "email": "vsanchez.full@example.com",
      "phone": "+506 8888 2345",
      "website": "linkedin.com/in/valerias-dev"
    },
    "workExperience": [
      {
        "company": "HealthTech CR",
        "startDate": "2021-08",
        "endDate": "Present",
        "position": "Fullstack Developer",
        "description": "Diseno e implementacion de una aplicacion para centros de acondicionamiento fisico. Desarrollo de sistemas de login con control de roles, seguimiento de historial y gestion de mediciones fisicas usando Express y PostgreSQL."
      }
    ],
    "education": [
      {
        "institution": "Instituto Tecnologico de Costa Rica",
        "degree": "Licenciatura",
        "title": "Ingenieria en Computacion",
        "startDate": "2015",
        "endDate": "2020"
      }
    ],
    "skills": [
      "javascript",
      "express",
      "postgresql",
      "vue",
      "docker",
      "github_actions",
      "sql",
      "linux_administration"
    ]
  },
  {
    "name": "Esteban Quiros",
    "introduction": "Data Engineer / ML Developer con 3.5 anos de experiencia. Especializado en el analisis de datos estructurados para la deteccion de anomalias y la integracion de modulos de inteligencia artificial en aplicaciones tradicionales.",
    "contactInformation": {
      "email": "equiros.data@example.com",
      "phone": "+506 8888 3456",
      "website": "kaggle.com/equiros"
    },
    "workExperience": [
      {
        "company": "Fintech Analytics CR",
        "startDate": "2022-03",
        "endDate": "Present",
        "position": "Machine Learning Engineer",
        "description": "Desarrollo de modelos de clustering (K-Means) y algoritmos de deteccion de anomalias para plataformas de analisis de riesgo financiero y evaluacion de estabilidad."
      },
      {
        "company": "DataCorp",
        "startDate": "2021-01",
        "endDate": "2022-02",
        "position": "Data Analyst",
        "description": "Limpieza de datos y automatizacion de reportes utilizando Python y librerias de analisis."
      }
    ],
    "education": [
      {
        "institution": "Universidad de Costa Rica",
        "degree": "Bachillerato",
        "title": "Estadistica",
        "startDate": "2016",
        "endDate": "2020"
      }
    ],
    "skills": [
      "python",
      "machine_learning_fundamentals",
      "scikit_learn",
      "rag",
      "sql",
      "data_science",
      "pandas",
      "jupyter"
    ]
  },
  {
    "name": "Silvia Navarro",
    "introduction": "Ingeniera de Calidad de Software (QA Automation) Mid-Level. Dedicada a garantizar la estabilidad del software mediante estrategias de pruebas automatizadas y metodologias rigurosas de aseguramiento de calidad.",
    "contactInformation": {
      "email": "snavarro.qa@example.com",
      "phone": "+506 8888 4567",
      "website": "github.com/silvian-qa"
    },
    "workExperience": [
      {
        "company": "EduSystems CR",
        "startDate": "2021-06",
        "endDate": "Present",
        "position": "QA Automation Engineer",
        "description": "Implementacion de estrategias de testing para sistemas universitarios. Diseno de pruebas de caja negra, de caja blanca y analisis FMEA, integrando scripts de automatizacion en los pipelines de CI/CD."
      }
    ],
    "education": [
      {
        "institution": "Universidad Latina",
        "degree": "Bachillerato",
        "title": "Ingenieria de Software",
        "startDate": "2017",
        "endDate": "2021"
      }
    ],
    "skills": [
      "javascript",
      "python",
      "gitlab_ci",
      "agile_mindset",
      "scrum",
      "technical_documentation",
      "rest_api"
    ]
  },
  {
    "name": "Jorge Chaves",
    "introduction": "Backend Developer Mid-Level con 4.5 anos de experiencia. Fuerte inclinacion hacia la logica de programacion compleja, el diseno de agentes autonomos y sistemas de emparejamiento de datos.",
    "contactInformation": {
      "email": "jchaves.backend@example.com",
      "phone": "+506 8888 5678",
      "website": "jorgechaves.dev"
    },
    "workExperience": [
      {
        "company": "HR Tech Solutions",
        "startDate": "2021-09",
        "endDate": "Present",
        "position": "Backend Developer",
        "description": "Diseno de la logica central para sistemas de seguimiento de candidatos (ATS). Desarrollo de motores de negociacion basados en reglas y optimizacion de consultas en bases de datos relacionales."
      },
      {
        "company": "StartUp CR",
        "startDate": "2019-10",
        "endDate": "2021-08",
        "position": "Junior Backend Developer",
        "description": "Mantenimiento de microservicios en Express y soporte a integraciones de terceros."
      }
    ],
    "education": [
      {
        "institution": "Cenfotec",
        "degree": "Tecnico Superior",
        "title": "Desarrollo de Software",
        "startDate": "2017",
        "endDate": "2019"
      }
    ],
    "skills": [
      "javascript",
      "express",
      "postgresql",
      "microservices",
      "event_driven_architecture",
      "solid_principles",
      "git"
    ]
  }
]